pillaralgos_dev/__init__.py
pillaralgos_dev/dev_helpers.py
pillaralgos_dev/sanity_checks.py
pillaralgos_dev-0.1.5.dist-info/WHEEL
pillaralgos_dev-0.1.5.dist-info/METADATA
pillaralgos_dev-0.1.5.dist-info/RECORD
