Metadata-Version: 2.1
Name: pillaralgos-dev
Version: 0.1.5
Summary: Library containing some basic, commonly used functions during the creation and analysis of algorithms for Pillar
License: GPL-3.0-or-later
Author: Peter Gates
Author-email: pgate89@gmail.com
Requires-Python: >=3.8,<4.0
Classifier: License :: OSI Approved :: GNU General Public License v3 or later (GPLv3+)
Classifier: Programming Language :: Python :: 3
Classifier: Programming Language :: Python :: 3.8
Classifier: Programming Language :: Python :: 3.9
Requires-Dist: boto3 (>=1.17.49,<2.0.0)
Requires-Dist: matplotlib (>=3.4.1,<4.0.0)
Requires-Dist: numpy (>=1.20.2,<2.0.0)
Requires-Dist: pandas (>=1.2.3,<2.0.0)
Requires-Dist: seaborn (>=0.11.1,<0.12.0)
Project-URL: Bug Tracker, https://github.com/pillargg/twitch_chat_analysis/issues
Project-URL: Github, https://github.com/pillargg/twitch_chat_analysis/
Project-URL: Pillar, https://pillar.gg
